{
  "author": {
    "id": "author:damodar-dahal",
    "name": "Damodar Dahal",
    "slug": "damodar-dahal"
  },
  "change_description": "Initial sourcing from 2079 election results",
  "created_at": "2025-11-14T01:32:24.611720Z",
  "entity_or_relationship_id": "entity:person/chandan-kumar-yadav",
  "snapshot": {
    "attributes": {
      "election_council_misc": {
        "institution": null,
        "other_details": null,
        "qualification": {
          "en": {
            "provenance": "translation_service",
            "value": "Education N/A"
          },
          "ne": {
            "provenance": "imported",
            "value": "Education N/A"
          }
        }
      }
    },
    "attributions": [
      {
        "details": {
          "en": {
            "provenance": "human",
            "value": "2079 Election Results - imported 2025-11-12"
          },
          "ne": {
            "provenance": "human",
            "value": "२०७९ निर्वाचन परिणाम - आयात मिति 2025-11-12 A.D."
          }
        },
        "title": {
          "en": {
            "provenance": "human",
            "value": "Nepal Election Commission - 2079 results"
          },
          "ne": {
            "provenance": "human",
            "value": "नेपाल निर्वाचन आयोग - २०७९ को नतिजा"
          }
        }
      }
    ],
    "contacts": null,
    "created_at": "2025-11-14T01:32:24.611722Z",
    "description": null,
    "electoral_details": {
      "candidacies": [
        {
          "candidate_id": 334140,
          "constituency_id": "entity:location/constituency/bara-2",
          "elected": false,
          "election_type": "provincial",
          "election_year": 2079,
          "pa_subdivision": "B",
          "party_id": "entity:organization/political_party/nepal-workers-peasants-party",
          "position": "provincial_assembly",
          "symbol": {
            "nec_id": 12,
            "symbol_name": {
              "en": {
                "provenance": "translation_service",
                "value": "Madal"
              },
              "ne": {
                "provenance": "imported",
                "value": "मादल"
              }
            },
            "url": null
          },
          "votes_received": 78
        }
      ]
    },
    "id": "entity:person/chandan-kumar-yadav",
    "identifiers": [
      {
        "name": {
          "en": {
            "provenance": "human",
            "value": "nec_candidate_id"
          },
          "ne": {
            "provenance": "human",
            "value": "निर्वाचन आयोग दर्ता नं०]"
          }
        },
        "scheme": "other",
        "url": null,
        "value": "334140"
      }
    ],
    "misspelled_names": null,
    "names": [
      {
        "en": {
          "family": null,
          "full": "Chandan Kumar Yadav",
          "given": null,
          "middle": null,
          "prefix": null,
          "suffix": null
        },
        "kind": "PRIMARY",
        "ne": {
          "family": null,
          "full": "चन्दन कुमार यादव",
          "given": null,
          "middle": null,
          "prefix": null,
          "suffix": null
        }
      }
    ],
    "personal_details": {
      "address": {
        "description": null,
        "description2": {
          "en": {
            "provenance": "translation_service",
            "value": "Bara Suwarna Rural Municipality"
          },
          "ne": {
            "provenance": "imported",
            "value": "बारा सुवर्ण गाउँपालिका"
          }
        },
        "location_id": null
      },
      "birth_date": "1995-09-19",
      "birth_place": null,
      "citizenship_place": {
        "description": null,
        "description2": null,
        "location_id": "entity:location/district/bara"
      },
      "education": null,
      "father_name": {
        "en": {
          "provenance": "translation_service",
          "value": "Ramaekwal Prasad Yadav"
        },
        "ne": {
          "provenance": "imported",
          "value": "रामएकवाल प्रसाद यादव"
        }
      },
      "gender": "male",
      "mother_name": null,
      "positions": null,
      "spouse_name": {
        "en": {
          "provenance": "translation_service",
          "value": "Anju Yadav"
        },
        "ne": {
          "provenance": "imported",
          "value": "अन्जु यादव"
        }
      }
    },
    "pictures": [
      {
        "description": "Source: Nepal Election Commission",
        "height": null,
        "type": "thumb",
        "url": "https://assets.nes.newnepal.org/assets/images/election-commission-2079-pictures/334140.jpg",
        "width": null
      }
    ],
    "short_description": null,
    "slug": "chandan-kumar-yadav",
    "sub_type": null,
    "tags": [
      "provincial-election-2079-candidate"
    ],
    "type": "person",
    "version_summary": {
      "author": {
        "id": "author:damodar-dahal",
        "name": "Damodar Dahal",
        "slug": "damodar-dahal"
      },
      "change_description": "Initial sourcing from 2079 election results",
      "created_at": "2025-11-14T01:32:24.611720Z",
      "entity_or_relationship_id": "entity:person/chandan-kumar-yadav",
      "id": "version:entity:person/chandan-kumar-yadav:1",
      "type": "ENTITY",
      "version_number": 1
    }
  },
  "type": "ENTITY",
  "version_number": 1
}