{
  "area": 1309.0,
  "attributes": {
    "headquarter": {
      "en": {
        "provenance": "imported",
        "value": "Pyuthan"
      },
      "ne": {
        "provenance": "imported",
        "value": "प्युठान"
      }
    }
  },
  "attributions": [
    {
      "details": {
        "en": {
          "provenance": "imported",
          "value": "https://github.com/sagautam5/local-states-nepal (imported 2025-11-09)"
        },
        "ne": null
      },
      "title": {
        "en": {
          "provenance": "imported",
          "value": "Sagar Gautam (GitHub)"
        },
        "ne": null
      }
    }
  ],
  "contacts": null,
  "created_at": "2025-11-09T16:26:58.355009Z",
  "description": null,
  "identifiers": [
    {
      "scheme": "other",
      "url": null,
      "value": "54"
    },
    {
      "scheme": "website",
      "url": "https://dccpyuthan.gov.np/",
      "value": "https://dccpyuthan.gov.np/"
    }
  ],
  "lat": null,
  "lng": null,
  "misspelled_names": null,
  "names": [
    {
      "en": {
        "family": null,
        "full": "Pyuthan",
        "given": null,
        "middle": null,
        "prefix": null,
        "suffix": null
      },
      "kind": "PRIMARY",
      "ne": {
        "family": null,
        "full": "प्युठान",
        "given": null,
        "middle": null,
        "prefix": null,
        "suffix": null
      }
    }
  ],
  "parent": "entity:location/province/lumbini",
  "pictures": null,
  "short_description": null,
  "slug": "pyuthan",
  "sub_type": "district",
  "tags": null,
  "type": "location",
  "version_summary": {
    "author": {
      "id": "author:damodar-dahal",
      "name": "Damodar Dahal",
      "slug": "damodar-dahal"
    },
    "change_description": "Initial sourcing",
    "created_at": "2025-11-09T16:26:58.355007Z",
    "entity_or_relationship_id": "entity:location/district/pyuthan",
    "type": "ENTITY",
    "version_number": 1
  }
}